{
  "magic": {
    "Blocos Modernos": [
      {
        "name": "Theros",
        "sets": [
          {"name": "Viagem para Nyx", "set_code": "JOU", "img_url": "https://draftsim.com/wp-content/uploads/2021/11/Journey-into-Nyx-set-symbol-300x282.png", "img_path": "imagens/mtg/Blocos Modernos/Theros/JOU.png"},
          {"name": "Nascidos dos Deuses", "set_code": "BNG", "img_url": "https://draftsim.com/wp-content/uploads/2021/11/Born-of-the-Gods-set-symbol.png", "img_path": "imagens/mtg/Blocos Modernos/Theros/BNG.png"},
          {"name": "Theros", "set_code": "THS", "img_url": "https://draftsim.com/wp-content/uploads/2021/11/Theros-set-symbol.png", "img_path": "imagens/mtg/Blocos Modernos/Theros/THS.png"}
        ]
      },
      {
        "name": "Retorno a Ravnica",
        "sets": [
          {"name": "Labirinto do Dragão", "set_code": "DGM", "img_url": "https://draftsim.com/wp-content/uploads/2021/11/Dragons-Maze-set-symbol.png", "img_path": "imagens/mtg/Blocos Modernos/Retorno a Ravnica/DGM.png"},
          {"name": "Portões Violados", "set_code": "GTC", "img_url": "https://draftsim.com/wp-content/uploads/2021/11/Gatecrash-set-symbol.png", "img_path": "imagens/mtg/Blocos Modernos/Retorno a Ravnica/GTC.png"},
          {"name": "Retorno a Ravnica", "set_code": "RTR", "img_url": "https://draftsim.com/wp-content/uploads/2021/11/Return-to-Ravnica-set-symbol-300x288.png", "img_path": "imagens/mtg/Blocos Modernos/Retorno a Ravnica/RTR.png"}
        ]
      },
      {
        "name": "Innistrad",
        "sets": [
          {"name": "Retorno de Avacyn", "set_code": "AVR", "img_url": "https://draftsim.com/wp-content/uploads/2021/11/Avacyn-Restored-set-symbol-296x300.png", "img_path": "imagens/mtg/Blocos Modernos/Innistrad/AVR.png"},
          {"name": "Ascensão das Trevas", "set_code": "DKA", "img_url": "https://draftsim.com/wp-content/uploads/2021/11/Dark-Ascension-set-symbol.png", "img_path": "imagens/mtg/Blocos Modernos/Innistrad/DKA.png"},
          {"name": "Innistrad", "set_code": "ISD", "img_url": "https://draftsim.com/wp-content/uploads/2021/11/Innistrad-set-symbol-300x272.png", "img_path": "imagens/mtg/Blocos Modernos/Innistrad/ISD.png"}
        ]
      }
    ],
    "Blocos Clássicos": [
       {"name": "Cicatrizes de Mirrodin", "sets": [
          {"name": "Nova Phyrexia", "set_code": "NPH", "img_url": "https://draftsim.com/wp-content/uploads/2021/11/New-Phyrexia-set-symbol-205x300.png", "img_path": "imagens/mtg/Blocos Clássicos/Cicatrizes de Mirrodin/NPH.png"},
          {"name": "Mirrodin Sitiada", "set_code": "MBS", "img_url": "https://draftsim.com/wp-content/uploads/2021/11/Mirrodin-Besieged-set-symbol-239x300.png", "img_path": "imagens/mtg/Blocos Clássicos/Cicatrizes de Mirrodin/MBS.png"},
          {"name": "Cicatrizes de Mirrodin", "set_code": "SOM", "img_url": "https://draftsim.com/wp-content/uploads/2021/11/Scars-of-Mirrodin-set-symbol-300x300.png", "img_path": "imagens/mtg/Blocos Clássicos/Cicatrizes de Mirrodin/SOM.png"}
        ]},
        {"name": "Zendikar", "sets": [
            {"name": "Ascensão dos Eldrazi", "set_code": "ROE", "img_url": "https://draftsim.com/wp-content/uploads/2021/11/Rise-of-the-Eldrazi-set-symbol-300x276.png", "img_path": "imagens/mtg/Blocos Clássicos/Zendikar/ROE.png"},
            {"name": "Despertar do Mundo", "set_code": "WWK", "img_url": "https://draftsim.com/wp-content/uploads/2021/11/Worldwake-set-symbol.png", "img_path": "imagens/mtg/Blocos Clássicos/Zendikar/WWK.png"},
            {"name": "Zendikar", "set_code": "ZEN", "img_url": "https://draftsim.com/wp-content/uploads/2021/11/Zendikar-set-symbol-218x300.png", "img_path": "imagens/mtg/Blocos Clássicos/Zendikar/ZEN.png"}
        ]}
    ],
    "Primórdios": [
         {"name": "Saga de Urza", "sets": [
            {"name": "Destino de Urza", "set_code": "UDS", "img_url": "https://draftsim.com/wp-content/uploads/2021/11/Urzas-Destiny-set-symbol-261x300.png", "img_path": "imagens/mtg/Primórdios/Saga de Urza/UDS.png"},
            {"name": "Legado de Urza", "set_code": "ULG", "img_url": "https://draftsim.com/wp-content/uploads/2021/11/Urzas-Legacy-set-symbol.png", "img_path": "imagens/mtg/Primórdios/Saga de Urza/ULG.png"},
            {"name": "Saga de Urza", "set_code": "USG", "img_url": "https://draftsim.com/wp-content/uploads/2021/11/Urzas-Saga-set-symbol.png", "img_path": "imagens/mtg/Primórdios/Saga de Urza/USG.png"}
        ]},
        {"name": "Tempestade", "sets": [
            {"name": "Êxodo", "set_code": "EXO", "img_url": "https://draftsim.com/wp-content/uploads/2021/11/Exodus-set-symbol-300x124.png", "img_path": "imagens/mtg/Primórdios/Tempestade/EXO.png"},
            {"name": "Fortaleza", "set_code": "STH", "img_url": "https://draftsim.com/wp-content/uploads/2021/11/Stronghold-set-symbol-290x300.png", "img_path": "imagens/mtg/Primórdios/Tempestade/STH.png"},
            {"name": "Tempestade", "set_code": "TMP", "img_url": "https://draftsim.com/wp-content/uploads/2021/11/Tempest-set-symbol-300x249.png", "img_path": "imagens/mtg/Primórdios/Tempestade/TMP.png"}
        ]},
         {"name": "Era Glacial", "sets": [
            {"name": "Alianças", "set_code": "ALL", "img_url": "https://draftsim.com/wp-content/uploads/2021/11/Alliances-set-symbol-300x132.png", "img_path": "imagens/mtg/Primórdios/Era Glacial/ALL.png"},
            {"name": "Era Glacial", "set_code": "ICE", "img_url": "https://draftsim.com/wp-content/uploads/2021/11/Ice-Age-set-symbol-288x300.png", "img_path": "imagens/mtg/Primórdios/Era Glacial/ICE.png"}
        ]},
        {"name": "Iniciais", "sets": [
            {"name": "Terras Natais", "set_code": "HML", "img_url": "https://draftsim.com/wp-content/uploads/2021/11/Homelands-set-symbol-300x295.png", "img_path": "imagens/mtg/Primórdios/Iniciais/HML.png"},
            {"name": "Fallen Empires", "set_code": "FEM", "img_url": "https://draftsim.com/wp-content/uploads/2021/11/Fallen-Empires-set-symbol.png", "img_path": "imagens/mtg/Primórdios/Iniciais/FEM.png"},
            {"name": "The Dark", "set_code": "DRK", "img_url": "https://draftsim.com/wp-content/uploads/2021/11/The-Dark-set-symbol.png", "img_path": "imagens/mtg/Primórdios/Iniciais/DRK.png"},
            {"name": "Lendas", "set_code": "LEG", "img_url": "https://draftsim.com/wp-content/uploads/2021/11/Legends-set-symbol-289x300.png", "img_path": "imagens/mtg/Primórdios/Iniciais/LEG.png"},
            {"name": "Antiquities", "set_code": "ATQ", "img_url": "https://draftsim.com/wp-content/uploads/2021/11/Antiquities-set-symbol-300x177.png", "img_path": "imagens/mtg/Primórdios/Iniciais/ATQ.png"},
            {"name": "Arabian Nights", "set_code": "ARN", "img_url": "https://draftsim.com/wp-content/uploads/2021/11/Arabian-Nights-set-symbol-300x139.png", "img_path": "imagens/mtg/Primórdios/Iniciais/ARN.png"}
        ]}
    ],
    "Coleções Base e Especiais": [
        {"name": "Core Sets", "sets": [
            {"name": "Magic 2014", "set_code": "M14", "img_url": "https://draftsim.com/wp-content/uploads/2021/11/Magic-2014-set-symbol-300x160.png", "img_path": "imagens/mtg/Coleções Base e Especiais/Core Sets/M14.png"},
            {"name": "Magic 2013", "set_code": "M13", "img_url": "https://draftsim.com/wp-content/uploads/2021/11/Magic-2013-set-symbol.png", "img_path": "imagens/mtg/Coleções Base e Especiais/Core Sets/M13.png"},
            {"name": "Magic 2012", "set_code": "M12", "img_url": "https://draftsim.com/wp-content/uploads/2021/11/Magic-2012-set-symbol-300x160.png", "img_path": "imagens/mtg/Coleções Base e Especiais/Core Sets/M12.png"}
        ]},
         {"name": "Especiais", "sets": [
            {"name": "Conspiracy", "set_code": "CNS"}, {"name": "Commander 2014", "set_code": "C14"}, {"name": "Commander 2013", "set_code": "C13"}
        ]}
    ]
  },
  "pokemon": {
    "Moderno": [
        {"name": "SV", "sets": [
            {"name": "Fábulas Nebulosas", "set_code": "SV09", "sigla": "NFA", "img_url": "https://archives.bulbagarden.net/media/upload/thumb/7/74/SetSymbolShrouded_Fable.png/40px-SetSymbolShrouded_Fable.png", "img_path": "imagens/pokemon/Moderno/SV/NFA.png"},
            {"name": "Máscaras do Crepúsculo", "set_code": "SV08", "sigla": "TWM", "img_url": "https://archives.bulbagarden.net/media/upload/thumb/6/65/SetSymbolTwilight_Masquerade.png/40px-SetSymbolTwilight_Masquerade.png", "img_path": "imagens/pokemon/Moderno/SV/TWM.png"}
        ]}
    ]
  }
}
