 [
          {
  "username": "Admin",
  "password_hash": "b80f3145c6be886bed538f59e6f595797667b34e081212ccaffdc3c37a9fe368",
  "permissions": {
    "ygo": true,
    "mtg": true,
    "pkm": true,
    "op": true,
    "fab": true,
    "dgm": true,
    "can_import_db": true,
    "can_manage_users": true,
    "can_update_online_db": true
  }
}
{
  "username": "TesteYGO",
  "password_hash": "8887a4f9a51678383a00c8442aa5520e51522dc57ed451837f30df05ea6b1a7d",
  "permissions": {
    "ygo": true,
    "mtg": false,
    "pkm": false,
    "op": false,
    "fab": false,
    "dgm": false,
    "can_import_db": false,
    "can_manage_users": false,
    "can_update_online_db": true
  }
}
  
        ]
